<?xml version = '1.0' encoding = 'UTF-8'?>
<RoleOraclev10g class="oracle.dbtools.crest.model.design.storage.oracle.v10g.RoleOraclev10g" name="RAPIHOMO" directorySegmentName="seg_0" id="03F90CA7-F113-9767-3F97-33CDCF7EFF15">
<sourceConnName>PROD</sourceConnName>
<sourceObjName>RAPIHOMO</sourceObjName>
<createdBy>CDETKE</createdBy>
<createdTime>2022-01-04 18:03:30 UTC</createdTime>
<ownerDesignName>WEBSERVICERP-BK</ownerDesignName>
<permissions>
<Permission class="oracle.dbtools.crest.model.design.storage.oracle.v10g.PermissionsOraclev10g" name="Permissions109" id="D1DC60EF-2A92-3CF1-909D-AD2501DCEAEC">
<createdBy>CDETKE</createdBy>
<createdTime>2022-01-04 18:03:30 UTC</createdTime>
<ownerDesignName>WEBSERVICERP-BK</ownerDesignName>
<privileges>DELETE, INSERT, SELECT, UPDATE</privileges>
<table>CBBDC9F0-729E-A691-95C0-549427A65053</table>
</Permission>
<Permission class="oracle.dbtools.crest.model.design.storage.oracle.v10g.PermissionsOraclev10g" name="Permissions126" id="34F24F25-B2EB-3278-8485-F44527408029">
<createdBy>CDETKE</createdBy>
<createdTime>2022-01-04 18:03:30 UTC</createdTime>
<ownerDesignName>WEBSERVICERP-BK</ownerDesignName>
<privileges>DELETE, INSERT, SELECT, UPDATE</privileges>
<table>DE6E5B4B-FFB6-0F88-A422-E11F2BED41EB</table>
</Permission>
<Permission class="oracle.dbtools.crest.model.design.storage.oracle.v10g.PermissionsOraclev10g" name="Permissions135" id="5D862CC6-DECB-3304-7FFC-15BA5B94677F">
<createdBy>CDETKE</createdBy>
<createdTime>2022-01-04 18:03:30 UTC</createdTime>
<ownerDesignName>WEBSERVICERP-BK</ownerDesignName>
<privileges>REFERENCES</privileges>
<privilegesWithGrantOption>SELECT</privilegesWithGrantOption>
<table>7E804EDF-C5FA-E6CD-7EC4-3C5AC9B03895</table>
</Permission>
<Permission class="oracle.dbtools.crest.model.design.storage.oracle.v10g.PermissionsOraclev10g" name="Permissions157" id="51557776-536F-6F1B-3890-E803AF0D0EDF">
<createdBy>CDETKE</createdBy>
<createdTime>2022-01-04 18:03:30 UTC</createdTime>
<ownerDesignName>WEBSERVICERP-BK</ownerDesignName>
<privileges>DELETE, INSERT, SELECT, UPDATE</privileges>
<table>56898E8A-66B0-E768-FAE4-1D106C43E0E0</table>
</Permission>
<Permission class="oracle.dbtools.crest.model.design.storage.oracle.v10g.PermissionsOraclev10g" name="Permissions58" id="EB01AE68-7196-EC47-D632-53AE1B94326C">
<createdBy>CDETKE</createdBy>
<createdTime>2022-01-04 18:03:30 UTC</createdTime>
<ownerDesignName>WEBSERVICERP-BK</ownerDesignName>
<privileges>REFERENCES</privileges>
<privilegesWithGrantOption>SELECT</privilegesWithGrantOption>
<table>80B68678-7C49-E212-35AF-0A3E3BDDD305</table>
</Permission>
<Permission class="oracle.dbtools.crest.model.design.storage.oracle.v10g.PermissionsOraclev10g" name="Permissions6" id="2CAB9643-8EDD-CA6E-4CAF-7DFCC1D3696F">
<createdBy>CDETKE</createdBy>
<createdTime>2022-01-04 18:03:30 UTC</createdTime>
<ownerDesignName>WEBSERVICERP-BK</ownerDesignName>
<privileges>REFERENCES</privileges>
<privilegesWithGrantOption>SELECT</privilegesWithGrantOption>
<table>94A215B2-8F9A-F955-42D6-D0C0A644CCE4</table>
</Permission>
</permissions>
</RoleOraclev10g>